alog/__init__.py
alog/alogger.py
alog-1.2.0.dist-info/LICENSE
alog-1.2.0.dist-info/METADATA
alog-1.2.0.dist-info/WHEEL
alog-1.2.0.dist-info/top_level.txt
alog-1.2.0.dist-info/RECORD
