Metadata-Version: 2.1
Name: alog
Version: 1.2.0
Summary: Your goto Python logging without panic on context swtich
Home-page: https://github.com/keitheis/alog
Author: Keith Yang
Author-email: yang@keitheis.org
License: Apache 2.0
Keywords: simple basic application logging print
Platform: UNKNOWN
Classifier: Development Status :: 5 - Production/Stable
Classifier: Intended Audience :: Developers
Classifier: License :: OSI Approved :: Apache Software License
Classifier: Topic :: System :: Logging
Classifier: Topic :: Software Development
Classifier: Programming Language :: Python
Classifier: Programming Language :: Python :: 2.7
Classifier: Programming Language :: Python :: 3
Classifier: Programming Language :: Python :: 3.6
Classifier: Programming Language :: Python :: 3.7
Classifier: Programming Language :: Python :: 3.8
Classifier: Programming Language :: Python :: 3.9
Classifier: Programming Language :: Python :: Implementation :: CPython
Classifier: Programming Language :: Python :: Implementation :: PyPy
License-File: LICENSE
Provides-Extra: docs
Requires-Dist: Sphinx (>=1.3.1) ; extra == 'docs'
Provides-Extra: testing
Requires-Dist: pytest-cov ; extra == 'testing'
